<?xml version="1.0" encoding="utf-8"?>
<odoo>
    <data noupdate="1">
        <!-- Products, warehouse MDW, and locations: see demo_inventory_master.xml -->

        <record id="base.user_admin" model="res.users">
            <field name="groups_id" eval="[(4, ref('stock.group_stock_multi_warehouses')), (4, ref('stock_reservation_engine.group_stock_reservation_manager'))]"/>
        </record>

        <record id="partner_demo_reservation_user" model="res.partner">
            <field name="name">Demo Reservation User</field>
            <field name="email">demo.res.user@test.local</field>
        </record>
        <record id="user_demo_reservation" model="res.users">
            <field name="name">Demo Reservation User</field>
            <field name="login">demo_res_user</field>
            <field name="password">demo_res_user</field>
            <field name="partner_id" ref="partner_demo_reservation_user"/>
            <field name="company_id" ref="base.main_company"/>
            <field name="company_ids" eval="[(6, 0, [ref('base.main_company')])]"/>
            <field name="groups_id" eval="[(6, 0, [ref('base.group_user'), ref('stock.group_stock_user'), ref('stock.group_stock_multi_warehouses'), ref('stock_reservation_engine.group_stock_reservation_user')])]"/>
        </record>

        <!-- === Reservation batches (quantities completed in hooks.py) === -->

        <record id="demo_batch_draft" model="stock.reservation.batch">
            <field name="request_user_id" ref="base.user_admin"/>
            <field name="company_id" ref="base.main_company"/>
            <field name="state">draft</field>
            <field name="priority">2</field>
        </record>
        <record id="demo_line_full" model="stock.reservation.line">
            <field name="batch_id" ref="demo_batch_draft"/>
            <field name="product_id" model="product.template" eval="obj(ref('stock_reservation_engine.demo_pt_full')).product_variant_ids[:1].id"/>
            <field name="requested_qty">5</field>
            <field name="location_id" model="stock.warehouse" eval="obj(ref('stock_reservation_engine.warehouse_demo_mdw')).lot_stock_id.id"/>
            <field name="note">Confirm then allocate: full allocation (Demo Product A on Shelf A/B).</field>
        </record>

        <record id="demo_batch_partial" model="stock.reservation.batch">
            <field name="request_user_id" ref="base.user_admin"/>
            <field name="company_id" ref="base.main_company"/>
            <field name="state">confirmed</field>
            <field name="priority">3</field>
        </record>
        <record id="demo_line_partial" model="stock.reservation.line">
            <field name="batch_id" ref="demo_batch_partial"/>
            <field name="product_id" model="product.template" eval="obj(ref('stock_reservation_engine.demo_pt_partial')).product_variant_ids[:1].id"/>
            <field name="requested_qty">40</field>
            <field name="location_id" model="stock.warehouse" eval="obj(ref('stock_reservation_engine.warehouse_demo_mdw')).lot_stock_id.id"/>
            <field name="note">Demo Product B: low on-hand vs request → partial.</field>
        </record>

        <record id="demo_batch_empty" model="stock.reservation.batch">
            <field name="request_user_id" ref="base.user_admin"/>
            <field name="company_id" ref="base.main_company"/>
            <field name="state">confirmed</field>
            <field name="priority">1</field>
        </record>
        <record id="demo_line_empty" model="stock.reservation.line">
            <field name="batch_id" ref="demo_batch_empty"/>
            <field name="product_id" model="product.template" eval="obj(ref('stock_reservation_engine.demo_pt_empty')).product_variant_ids[:1].id"/>
            <field name="requested_qty">10</field>
            <field name="location_id" model="stock.warehouse" eval="obj(ref('stock_reservation_engine.warehouse_demo_mdw')).lot_stock_id.id"/>
            <field name="note">Demo Product C: no stock → not_available.</field>
        </record>

        <record id="demo_batch_mixed" model="stock.reservation.batch">
            <field name="request_user_id" ref="base.user_admin"/>
            <field name="company_id" ref="base.main_company"/>
            <field name="state">confirmed</field>
            <field name="priority">2</field>
        </record>
        <record id="demo_line_mixed_a" model="stock.reservation.line">
            <field name="batch_id" ref="demo_batch_mixed"/>
            <field name="product_id" model="product.template" eval="obj(ref('stock_reservation_engine.demo_pt_full')).product_variant_ids[:1].id"/>
            <field name="requested_qty">3</field>
            <field name="location_id" model="stock.warehouse" eval="obj(ref('stock_reservation_engine.warehouse_demo_mdw')).lot_stock_id.id"/>
            <field name="note">Mixed batch — full line.</field>
        </record>
        <record id="demo_line_mixed_b" model="stock.reservation.line">
            <field name="batch_id" ref="demo_batch_mixed"/>
            <field name="product_id" model="product.template" eval="obj(ref('stock_reservation_engine.demo_pt_partial')).product_variant_ids[:1].id"/>
            <field name="requested_qty">99</field>
            <field name="location_id" model="stock.warehouse" eval="obj(ref('stock_reservation_engine.warehouse_demo_mdw')).lot_stock_id.id"/>
            <field name="note">Mixed batch — partial line.</field>
        </record>
        <record id="demo_line_mixed_c" model="stock.reservation.line">
            <field name="batch_id" ref="demo_batch_mixed"/>
            <field name="product_id" model="product.template" eval="obj(ref('stock_reservation_engine.demo_pt_empty')).product_variant_ids[:1].id"/>
            <field name="requested_qty">2</field>
            <field name="location_id" model="stock.warehouse" eval="obj(ref('stock_reservation_engine.warehouse_demo_mdw')).lot_stock_id.id"/>
            <field name="note">Mixed batch — not_available line.</field>
        </record>

        <record id="demo_batch_dual_full" model="stock.reservation.batch">
            <field name="request_user_id" ref="base.user_admin"/>
            <field name="company_id" ref="base.main_company"/>
            <field name="state">confirmed</field>
            <field name="priority">2</field>
        </record>
        <record id="demo_line_dual_1" model="stock.reservation.line">
            <field name="batch_id" ref="demo_batch_dual_full"/>
            <field name="product_id" model="product.template" eval="obj(ref('stock_reservation_engine.demo_pt_full')).product_variant_ids[:1].id"/>
            <field name="requested_qty">4</field>
            <field name="location_id" model="stock.warehouse" eval="obj(ref('stock_reservation_engine.warehouse_demo_mdw')).lot_stock_id.id"/>
        </record>
        <record id="demo_line_dual_2" model="stock.reservation.line">
            <field name="batch_id" ref="demo_batch_dual_full"/>
            <field name="product_id" model="product.template" eval="obj(ref('stock_reservation_engine.demo_pt_full')).product_variant_ids[:1].id"/>
            <field name="requested_qty">6</field>
            <field name="location_id" model="stock.warehouse" eval="obj(ref('stock_reservation_engine.warehouse_demo_mdw')).lot_stock_id.id"/>
            <field name="note">Same product, two lines → batch allocated when both succeed.</field>
        </record>

        <record id="demo_batch_cancelled" model="stock.reservation.batch">
            <field name="request_user_id" ref="base.user_admin"/>
            <field name="company_id" ref="base.main_company"/>
            <field name="state">cancelled</field>
            <field name="priority">1</field>
        </record>
        <record id="demo_line_cancel_a" model="stock.reservation.line">
            <field name="batch_id" ref="demo_batch_cancelled"/>
            <field name="product_id" model="product.template" eval="obj(ref('stock_reservation_engine.demo_pt_full')).product_variant_ids[:1].id"/>
            <field name="requested_qty">2</field>
            <field name="location_id" model="stock.warehouse" eval="obj(ref('stock_reservation_engine.warehouse_demo_mdw')).lot_stock_id.id"/>
            <field name="state">cancelled</field>
        </record>

        <record id="demo_batch_done" model="stock.reservation.batch">
            <field name="request_user_id" ref="base.user_admin"/>
            <field name="company_id" ref="base.main_company"/>
            <field name="state">done</field>
            <field name="priority">1</field>
        </record>
        <record id="demo_line_done_1" model="stock.reservation.line">
            <field name="batch_id" ref="demo_batch_done"/>
            <field name="product_id" model="product.template" eval="obj(ref('stock_reservation_engine.demo_pt_full')).product_variant_ids[:1].id"/>
            <field name="requested_qty">2</field>
            <field name="allocated_qty">2</field>
            <field name="location_id" model="stock.warehouse" eval="obj(ref('stock_reservation_engine.warehouse_demo_mdw')).lot_stock_id.id"/>
            <field name="state">allocated</field>
            <field name="note">Static done state for UI filters.</field>
        </record>

        <record id="demo_batch_lot_ok" model="stock.reservation.batch">
            <field name="request_user_id" ref="base.user_admin"/>
            <field name="company_id" ref="base.main_company"/>
            <field name="state">confirmed</field>
            <field name="priority">2</field>
        </record>
        <record id="demo_line_lot_ok" model="stock.reservation.line">
            <field name="batch_id" ref="demo_batch_lot_ok"/>
            <field name="product_id" model="product.template" eval="obj(ref('stock_reservation_engine.demo_pt_lots')).product_variant_ids[:1].id"/>
            <field name="requested_qty">4</field>
            <field name="location_id" model="stock.warehouse" eval="obj(ref('stock_reservation_engine.warehouse_demo_mdw')).lot_stock_id.id"/>
            <field name="lot_id" ref="demo_lot_alpha"/>
            <field name="note">Preferred LOT-X-001 has stock in Cold Zone.</field>
        </record>

        <record id="demo_batch_lot_bad" model="stock.reservation.batch">
            <field name="request_user_id" ref="base.user_admin"/>
            <field name="company_id" ref="base.main_company"/>
            <field name="state">confirmed</field>
            <field name="priority">2</field>
        </record>
        <record id="demo_line_lot_bad" model="stock.reservation.line">
            <field name="batch_id" ref="demo_batch_lot_bad"/>
            <field name="product_id" model="product.template" eval="obj(ref('stock_reservation_engine.demo_pt_perishable_y')).product_variant_ids[:1].id"/>
            <field name="requested_qty">5</field>
            <field name="location_id" model="stock.warehouse" eval="obj(ref('stock_reservation_engine.warehouse_demo_mdw')).lot_stock_id.id"/>
            <field name="lot_id" ref="demo_lot_y_001"/>
            <field name="note">Preferred LOT-Y-001 has no on-hand stock (demo) → not_available.</field>
        </record>

        <record id="demo_batch_fefo" model="stock.reservation.batch">
            <field name="request_user_id" ref="base.user_admin"/>
            <field name="company_id" ref="base.main_company"/>
            <field name="state">confirmed</field>
            <field name="priority">2</field>
        </record>
        <record id="demo_line_fefo" model="stock.reservation.line">
            <field name="batch_id" ref="demo_batch_fefo"/>
            <field name="product_id" model="product.template" eval="obj(ref('stock_reservation_engine.demo_pt_lots')).product_variant_ids[:1].id"/>
            <field name="requested_qty">18</field>
            <field name="location_id" model="stock.warehouse" eval="obj(ref('stock_reservation_engine.warehouse_demo_mdw')).lot_stock_id.id"/>
            <field name="note">Perishable X: consumption follows earliest expiration (LOT-X-001 then LOT-X-002).</field>
        </record>

        <record id="demo_batch_shelf_parent" model="stock.reservation.batch">
            <field name="request_user_id" ref="base.user_admin"/>
            <field name="company_id" ref="base.main_company"/>
            <field name="state">confirmed</field>
            <field name="priority">2</field>
        </record>
        <record id="demo_line_shelf_parent" model="stock.reservation.line">
            <field name="batch_id" ref="demo_batch_shelf_parent"/>
            <field name="product_id" model="product.template" eval="obj(ref('stock_reservation_engine.demo_pt_full')).product_variant_ids[:1].id"/>
            <field name="requested_qty">8</field>
            <field name="location_id" model="stock.warehouse" eval="obj(ref('stock_reservation_engine.warehouse_demo_mdw')).lot_stock_id.id"/>
            <field name="note">Stock only under Shelf A/B; line uses parent MDW/Stock → child_of match.</field>
        </record>

        <record id="demo_batch_demo_user_owned" model="stock.reservation.batch">
            <field name="request_user_id" ref="user_demo_reservation"/>
            <field name="company_id" ref="base.main_company"/>
            <field name="state">confirmed</field>
            <field name="priority">2</field>
        </record>
        <record id="demo_line_demo_user_owned" model="stock.reservation.line">
            <field name="batch_id" ref="demo_batch_demo_user_owned"/>
            <field name="product_id" model="product.template" eval="obj(ref('stock_reservation_engine.demo_pt_full')).product_variant_ids[:1].id"/>
            <field name="requested_qty">3</field>
            <field name="location_id" model="stock.warehouse" eval="obj(ref('stock_reservation_engine.warehouse_demo_mdw')).lot_stock_id.id"/>
            <field name="note">Owned by demo_res_user (record rules).</field>
        </record>

        <record id="demo_api_token" model="reservation.api.token">
            <field name="name">Demo reservation API (admin)</field>
            <field name="user_id" ref="base.user_admin"/>
            <field name="token">demo-reservation-api-token-change-me</field>
            <field name="active" eval="True"/>
        </record>
        <record id="demo_api_token_res_user" model="reservation.api.token">
            <field name="name">Demo reservation API (reservation user)</field>
            <field name="user_id" ref="user_demo_reservation"/>
            <field name="token">demo-res-user-api-token-change-me</field>
            <field name="active" eval="True"/>
        </record>
        <record id="demo_api_token_inactive" model="reservation.api.token">
            <field name="name">Inactive token (negative auth tests)</field>
            <field name="user_id" ref="base.user_admin"/>
            <field name="token">inactive-token-never-valid</field>
            <field name="active" eval="False"/>
        </record>
    </data>
</odoo>
